README.md
setup.py
TestAPackageH.egg-info/PKG-INFO
TestAPackageH.egg-info/SOURCES.txt
TestAPackageH.egg-info/dependency_links.txt
TestAPackageH.egg-info/requires.txt
TestAPackageH.egg-info/top_level.txt
hanalytics/profile/_init__.py
hanalytics/profile/profileBQ.py