Metadata-Version: 2.1
Name: TestAPackageH
Version: 0.2
Summary: A publishing test
Author: Test
